{
  "Antrag": {
    "counts_by_party": [
      { "party": "AfD", "count": 618 },
      { "party": "CDU/CSU", "count": 420 },
      { "party": "Die Linke", "count": 185 },
      { "party": "Grüne", "count": 81 },
      { "party": "FDP", "count": 16 },
      { "party": "SPD", "count": 1 }
    ],
    "timeline": {
      "months": [
        "2021-10",
        "2021-11",
        "2021-12",
        "2022-01",
        "2022-02",
        "2022-03",
        "2022-04",
        "2022-05",
        "2022-06",
        "2022-07",
        "2022-08",
        "2022-09",
        "2022-10",
        "2022-11",
        "2022-12",
        "2023-01",
        "2023-02",
        "2023-03",
        "2023-04",
        "2023-05",
        "2023-06",
        "2023-07",
        "2023-08",
        "2023-09",
        "2023-10",
        "2023-11",
        "2023-12",
        "2024-01",
        "2024-02",
        "2024-03",
        "2024-04",
        "2024-05",
        "2024-06",
        "2024-07",
        "2024-09",
        "2024-10",
        "2024-11",
        "2024-12",
        "2025-01",
        "2025-02"
      ],
      "series": [
        {
          "party": "CDU/CSU",
          "counts": [
            0, 2, 4, 2, 10, 11, 11, 7, 12, 13, 0, 16, 14, 21, 14, 13, 12, 14,
            10, 12, 16, 12, 0, 19, 15, 24, 16, 5, 10, 11, 14, 11, 28, 4, 12, 6,
            9, 8, 2, 0
          ]
        },
        {
          "party": "SPD",
          "counts": [
            1, 0, 0, 0, 0, 0, 0, 0, 0, 0, 0, 0, 0, 0, 0, 0, 0, 0, 0, 0, 0, 0, 0,
            0, 0, 0, 0, 0, 0, 0, 0, 0, 0, 0, 0, 0, 0, 0, 0, 0
          ]
        },
        {
          "party": "AfD",
          "counts": [
            1, 8, 8, 5, 10, 13, 10, 13, 9, 17, 1, 29, 17, 22, 13, 14, 19, 22,
            18, 32, 19, 13, 1, 22, 15, 19, 11, 11, 11, 11, 13, 18, 23, 12, 17,
            16, 76, 18, 11, 0
          ]
        },
        {
          "party": "Grüne",
          "counts": [
            1, 3, 4, 3, 2, 4, 1, 5, 1, 4, 0, 2, 3, 8, 0, 1, 0, 2, 2, 4, 2, 1, 0,
            1, 1, 3, 0, 2, 2, 2, 2, 1, 3, 3, 0, 3, 2, 0, 2, 1
          ]
        },
        {
          "party": "Die Linke",
          "counts": [
            0, 3, 6, 2, 6, 6, 9, 18, 9, 12, 0, 10, 10, 13, 3, 7, 6, 10, 9, 7, 7,
            10, 0, 7, 9, 6, 0, 0, 0, 0, 0, 0, 0, 0, 0, 0, 0, 0, 0, 0
          ]
        },
        {
          "party": "FDP",
          "counts": [
            0, 0, 0, 0, 0, 0, 0, 0, 0, 0, 0, 0, 0, 0, 0, 0, 0, 0, 0, 0, 0, 0, 0,
            0, 0, 0, 0, 0, 0, 0, 0, 0, 0, 0, 0, 0, 0, 7, 9, 0
          ]
        }
      ]
    },
    "word_freq": {
      "AfD": [
        { "wort": "deutschen", "tfidf": 0.00495, "rang": 1 },
        { "wort": "entlasten", "tfidf": 0.00439, "rang": 2 },
        { "wort": "verhindern", "tfidf": 0.003693, "rang": 3 },
        { "wort": "deutsche", "tfidf": 0.00342, "rang": 4 },
        { "wort": "erhalten", "tfidf": 0.003414, "rang": 5 },
        { "wort": "sicherstellen", "tfidf": 0.003385, "rang": 6 },
        { "wort": "mittelstand", "tfidf": 0.003182, "rang": 7 },
        { "wort": "entwicklungszusammenarbeit", "tfidf": 0.00317, "rang": 8 },
        { "wort": "energieversorgung", "tfidf": 0.00317, "rang": 9 },
        { "wort": "europäischen", "tfidf": 0.00297, "rang": 10 },
        { "wort": "beenden", "tfidf": 0.002616, "rang": 11 },
        { "wort": "transparenz", "tfidf": 0.002439, "rang": 12 },
        { "wort": "kernkraftwerke", "tfidf": 0.002386, "rang": 13 },
        { "wort": "stoppen", "tfidf": 0.00225, "rang": 14 },
        { "wort": "abschaffung", "tfidf": 0.002195, "rang": 15 },
        { "wort": "bürger", "tfidf": 0.002195, "rang": 16 },
        { "wort": "neu", "tfidf": 0.002154, "rang": 17 },
        { "wort": "einführung", "tfidf": 0.002154, "rang": 18 },
        { "wort": "bundesrepublik", "tfidf": 0.001989, "rang": 19 },
        { "wort": "massenmigration", "tfidf": 0.001989, "rang": 20 },
        { "wort": "afrikas", "tfidf": 0.001989, "rang": 21 },
        { "wort": "nord", "tfidf": 0.001989, "rang": 22 },
        { "wort": "sofortige", "tfidf": 0.001989, "rang": 23 },
        { "wort": "kostengünstige", "tfidf": 0.001989, "rang": 24 },
        { "wort": "stadt", "tfidf": 0.001989, "rang": 25 },
        { "wort": "deutschland", "tfidf": 0.001902, "rang": 26 },
        { "wort": "abschaffen", "tfidf": 0.001846, "rang": 27 },
        { "wort": "bewahren", "tfidf": 0.001846, "rang": 28 },
        { "wort": "maßnahmen", "tfidf": 0.001707, "rang": 29 },
        { "wort": "afrika", "tfidf": 0.001707, "rang": 30 },
        { "wort": "ausrichten", "tfidf": 0.001707, "rang": 31 },
        { "wort": "einleiten", "tfidf": 0.001707, "rang": 32 },
        { "wort": "förderung", "tfidf": 0.001707, "rang": 33 },
        { "wort": "geschäftsordnung", "tfidf": 0.001692, "rang": 34 },
        { "wort": "sofort", "tfidf": 0.001692, "rang": 35 },
        { "wort": "gewährleisten", "tfidf": 0.001692, "rang": 36 },
        { "wort": "sogenannte", "tfidf": 0.001591, "rang": 37 },
        { "wort": "kontext", "tfidf": 0.001591, "rang": 38 },
        { "wort": "afrikanischen", "tfidf": 0.001591, "rang": 39 },
        { "wort": "palästinensischen", "tfidf": 0.001591, "rang": 40 },
        { "wort": "ausland", "tfidf": 0.001591, "rang": 41 },
        { "wort": "stream", "tfidf": 0.001591, "rang": 42 },
        { "wort": "einsetzen", "tfidf": 0.001591, "rang": 43 },
        { "wort": "erinnerung", "tfidf": 0.001591, "rang": 44 },
        { "wort": "kriegsflüchtlinge", "tfidf": 0.001591, "rang": 45 },
        { "wort": "meinungsfreiheit", "tfidf": 0.001591, "rang": 46 },
        { "wort": "zuwanderung", "tfidf": 0.001591, "rang": 47 },
        { "wort": "ende", "tfidf": 0.001591, "rang": 48 },
        { "wort": "olympischen", "tfidf": 0.001591, "rang": 49 },
        { "wort": "corona-maßnahmen", "tfidf": 0.001591, "rang": 50 }
      ],
      "CDU/CSU": [
        { "wort": "mobilität", "tfidf": 0.004341, "rang": 1 },
        { "wort": "stärken", "tfidf": 0.00385, "rang": 2 },
        { "wort": "umsetzen", "tfidf": 0.003359, "rang": 3 },
        { "wort": "sofortprogramm", "tfidf": 0.003101, "rang": 4 },
        { "wort": "erhalten", "tfidf": 0.003042, "rang": 5 },
        { "wort": "nationale", "tfidf": 0.003042, "rang": 6 },
        { "wort": "deutschen", "tfidf": 0.002947, "rang": 7 },
        { "wort": "sicherstellen", "tfidf": 0.002879, "rang": 8 },
        { "wort": "verhindern", "tfidf": 0.002879, "rang": 9 },
        { "wort": "deutschland", "tfidf": 0.002777, "rang": 10 },
        { "wort": "entlasten", "tfidf": 0.002662, "rang": 11 },
        { "wort": "voranbringen", "tfidf": 0.002662, "rang": 12 },
        { "wort": "europa", "tfidf": 0.002639, "rang": 13 },
        { "wort": "beenden", "tfidf": 0.002639, "rang": 14 },
        { "wort": "russlands", "tfidf": 0.002481, "rang": 15 },
        { "wort": "wettbewerbsfähige", "tfidf": 0.002481, "rang": 16 },
        { "wort": "wirksam", "tfidf": 0.002399, "rang": 17 },
        { "wort": "führen", "tfidf": 0.002282, "rang": 18 },
        { "wort": "erfolg", "tfidf": 0.002282, "rang": 19 },
        { "wort": "verhandlungen", "tfidf": 0.002282, "rang": 20 },
        { "wort": "europäische", "tfidf": 0.002159, "rang": 21 },
        { "wort": "einen", "tfidf": 0.002105, "rang": 22 },
        { "wort": "schaffen", "tfidf": 0.002105, "rang": 23 },
        { "wort": "unterstützen", "tfidf": 0.002105, "rang": 24 },
        { "wort": "deutsche", "tfidf": 0.001965, "rang": 25 },
        { "wort": "digitale", "tfidf": 0.001901, "rang": 26 },
        { "wort": "umsetzung", "tfidf": 0.001901, "rang": 27 },
        { "wort": "lassen", "tfidf": 0.001901, "rang": 28 },
        { "wort": "wettbewerbsfähigkeit", "tfidf": 0.001901, "rang": 29 },
        { "wort": "raum", "tfidf": 0.001901, "rang": 30 },
        { "wort": "finanzierung", "tfidf": 0.001901, "rang": 31 },
        { "wort": "maßnahmen", "tfidf": 0.001901, "rang": 32 },
        { "wort": "krise", "tfidf": 0.001901, "rang": 33 },
        { "wort": "politikwechsel", "tfidf": 0.001861, "rang": 34 },
        { "wort": "beschließen", "tfidf": 0.001861, "rang": 35 },
        { "wort": "potentiale", "tfidf": 0.001861, "rang": 36 },
        { "wort": "speicherung", "tfidf": 0.001861, "rang": 37 },
        { "wort": "sorgen", "tfidf": 0.001861, "rang": 38 },
        { "wort": "verbrennungsmotors", "tfidf": 0.001861, "rang": 39 },
        { "wort": "reformen", "tfidf": 0.001861, "rang": 40 },
        { "wort": "europäisch", "tfidf": 0.001861, "rang": 41 },
        { "wort": "lieferung", "tfidf": 0.001861, "rang": 42 },
        { "wort": "bürokratiearm", "tfidf": 0.001861, "rang": 43 },
        { "wort": "barrierefreiheit", "tfidf": 0.001861, "rang": 44 },
        { "wort": "klimafreundliche", "tfidf": 0.001861, "rang": 45 },
        { "wort": "iranische", "tfidf": 0.001861, "rang": 46 },
        { "wort": "planungssicherheit", "tfidf": 0.001861, "rang": 47 },
        { "wort": "energien", "tfidf": 0.001861, "rang": 48 },
        { "wort": "schnelle", "tfidf": 0.001861, "rang": 49 },
        { "wort": "fachangestellten", "tfidf": 0.001861, "rang": 50 }
      ],
      "Die Linke": [
        { "wort": "verhindern", "tfidf": 0.008681, "rang": 1 },
        { "wort": "mieterinnen", "tfidf": 0.006905, "rang": 2 },
        { "wort": "beschäftigung", "tfidf": 0.006905, "rang": 3 },
        { "wort": "lohn", "tfidf": 0.005178, "rang": 4 },
        { "wort": "mitbestimmt", "tfidf": 0.005178, "rang": 5 },
        { "wort": "betriebliche", "tfidf": 0.005178, "rang": 6 },
        { "wort": "beenden", "tfidf": 0.004674, "rang": 7 },
        { "wort": "mitbestimmung", "tfidf": 0.004234, "rang": 8 },
        { "wort": "menschen", "tfidf": 0.004007, "rang": 9 },
        { "wort": "schuldenbremse", "tfidf": 0.003452, "rang": 10 },
        { "wort": "exportverbot", "tfidf": 0.003452, "rang": 11 },
        { "wort": "renteneinheit", "tfidf": 0.003452, "rang": 12 },
        { "wort": "ausgleichen", "tfidf": 0.003452, "rang": 13 },
        { "wort": "behinderungen", "tfidf": 0.003452, "rang": 14 },
        { "wort": "weltfriedenstag", "tfidf": 0.003452, "rang": 15 },
        { "wort": "vorschriften", "tfidf": 0.003452, "rang": 16 },
        { "wort": "eu-mercosur-abkommen", "tfidf": 0.003452, "rang": 17 },
        { "wort": "minijobs", "tfidf": 0.003452, "rang": 18 },
        { "wort": "wohnung", "tfidf": 0.003452, "rang": 19 },
        { "wort": "vorkaufsrecht", "tfidf": 0.003452, "rang": 20 },
        { "wort": "stunde", "tfidf": 0.003452, "rang": 21 },
        { "wort": "verfolgte", "tfidf": 0.003452, "rang": 22 },
        { "wort": "leid", "tfidf": 0.003452, "rang": 23 },
        { "wort": "konsumenten", "tfidf": 0.003452, "rang": 24 },
        { "wort": "grundnahrungsmittel", "tfidf": 0.003452, "rang": 25 },
        { "wort": "neun-euro-ticket", "tfidf": 0.003452, "rang": 26 },
        { "wort": "the", "tfidf": 0.003452, "rang": 27 },
        { "wort": "and", "tfidf": 0.003452, "rang": 28 },
        { "wort": "bundesbehörden", "tfidf": 0.003452, "rang": 29 },
        { "wort": "gute", "tfidf": 0.003339, "rang": 30 },
        { "wort": "sicherstellen", "tfidf": 0.003339, "rang": 31 },
        { "wort": "mindestlohn", "tfidf": 0.003175, "rang": 32 },
        { "wort": "strom", "tfidf": 0.003175, "rang": 33 },
        { "wort": "bürgergeld", "tfidf": 0.003175, "rang": 34 },
        { "wort": "mieter", "tfidf": 0.003175, "rang": 35 },
        { "wort": "streichen", "tfidf": 0.003175, "rang": 36 },
        { "wort": "arbeitsbedingungen", "tfidf": 0.003175, "rang": 37 },
        { "wort": "mehrwertsteuer", "tfidf": 0.003175, "rang": 38 },
        { "wort": "verbieten", "tfidf": 0.003175, "rang": 39 },
        { "wort": "sichern", "tfidf": 0.003125, "rang": 40 },
        { "wort": "statt", "tfidf": 0.002734, "rang": 41 },
        { "wort": "recht", "tfidf": 0.002671, "rang": 42 },
        { "wort": "gesetzlichen", "tfidf": 0.002671, "rang": 43 },
        { "wort": "inflation", "tfidf": 0.002671, "rang": 44 },
        { "wort": "braucht", "tfidf": 0.002671, "rang": 45 },
        { "wort": "geschäftsordnung", "tfidf": 0.002671, "rang": 46 },
        { "wort": "stoppen", "tfidf": 0.002344, "rang": 47 },
        { "wort": "deutschen", "tfidf": 0.002344, "rang": 48 },
        { "wort": "gesetzlich", "tfidf": 0.002117, "rang": 49 },
        { "wort": "einheit", "tfidf": 0.002117, "rang": 50 }
      ],
      "FDP": [
        { "wort": "kryptowährungen", "tfidf": 0.018472, "rang": 1 },
        { "wort": "bitcoin", "tfidf": 0.018472, "rang": 2 },
        { "wort": "öffentliche", "tfidf": 0.018472, "rang": 3 },
        { "wort": "effizientes", "tfidf": 0.018472, "rang": 4 },
        { "wort": "vergaberecht", "tfidf": 0.018472, "rang": 5 },
        { "wort": "verbrenner-aus", "tfidf": 0.018472, "rang": 6 },
        { "wort": "generationengerechte", "tfidf": 0.018472, "rang": 7 },
        { "wort": "rentenpolitik", "tfidf": 0.018472, "rang": 8 },
        { "wort": "kapitaldeckung", "tfidf": 0.018472, "rang": 9 },
        { "wort": "flexiblen", "tfidf": 0.018472, "rang": 10 },
        { "wort": "renteneintritt", "tfidf": 0.018472, "rang": 11 },
        { "wort": "absenkung", "tfidf": 0.018472, "rang": 12 },
        { "wort": "realitäten", "tfidf": 0.018472, "rang": 13 },
        { "wort": "züchtungsmethoden", "tfidf": 0.018472, "rang": 14 },
        { "wort": "nachhaltigere", "tfidf": 0.018472, "rang": 15 },
        { "wort": "blockade", "tfidf": 0.018472, "rang": 16 },
        { "wort": "parlamentarischer", "tfidf": 0.018472, "rang": 17 },
        { "wort": "mehrheitsfindung", "tfidf": 0.018472, "rang": 18 },
        { "wort": "ukraine-hilfen", "tfidf": 0.018472, "rang": 19 },
        { "wort": "update", "tfidf": 0.018472, "rang": 20 },
        { "wort": "leistungsgerechtigkeit", "tfidf": 0.018472, "rang": 21 },
        { "wort": "konsequenz", "tfidf": 0.018472, "rang": 22 },
        { "wort": "steuerzahler", "tfidf": 0.018472, "rang": 23 },
        { "wort": "luftverkehrsstandort", "tfidf": 0.018472, "rang": 24 },
        { "wort": "beflügeln", "tfidf": 0.018472, "rang": 25 },
        { "wort": "hausärztliche", "tfidf": 0.018472, "rang": 26 },
        { "wort": "entbudgetieren", "tfidf": 0.018472, "rang": 27 },
        { "wort": "realpolitik", "tfidf": 0.018472, "rang": 28 },
        { "wort": "weniger", "tfidf": 0.018472, "rang": 29 },
        { "wort": "risiko", "tfidf": 0.018472, "rang": 30 },
        { "wort": "selbstständigkeit", "tfidf": 0.018472, "rang": 31 },
        { "wort": "steht", "tfidf": 0.018472, "rang": 32 },
        { "wort": "seite", "tfidf": 0.018472, "rang": 33 },
        { "wort": "füllen", "tfidf": 0.018472, "rang": 34 },
        { "wort": "frauenhäuser", "tfidf": 0.018472, "rang": 35 },
        { "wort": "vergabe", "tfidf": 0.011326, "rang": 36 },
        { "wort": "entfesseln", "tfidf": 0.011326, "rang": 37 },
        { "wort": "klimaneutralen", "tfidf": 0.011326, "rang": 38 },
        { "wort": "aktienrente", "tfidf": 0.011326, "rang": 39 },
        { "wort": "schutzstatus", "tfidf": 0.011326, "rang": 40 },
        { "wort": "wolfs", "tfidf": 0.011326, "rang": 41 },
        { "wort": "weidetiere", "tfidf": 0.011326, "rang": 42 },
        { "wort": "netto", "tfidf": 0.011326, "rang": 43 },
        { "wort": "brutto", "tfidf": 0.011326, "rang": 44 },
        { "wort": "blick", "tfidf": 0.011326, "rang": 45 },
        { "wort": "ambulante", "tfidf": 0.011326, "rang": 46 },
        { "wort": "gesundheitssystem", "tfidf": 0.011326, "rang": 47 },
        { "wort": "voranbringen", "tfidf": 0.011326, "rang": 48 },
        { "wort": "wertschätzen", "tfidf": 0.011326, "rang": 49 },
        { "wort": "entschieden", "tfidf": 0.011326, "rang": 50 }
      ],
      "Grüne": [
        { "wort": "einsetzung", "tfidf": 0.014267, "rang": 1 },
        { "wort": "gremiums", "tfidf": 0.012293, "rang": 2 },
        { "wort": "aufgaben", "tfidf": 0.00922, "rang": 3 },
        { "wort": "absatz", "tfidf": 0.009041, "rang": 4 },
        { "wort": "gemäß", "tfidf": 0.009041, "rang": 5 },
        { "wort": "bundestages", "tfidf": 0.00765, "rang": 6 },
        { "wort": "artikel", "tfidf": 0.00765, "rang": 7 },
        { "wort": "satz", "tfidf": 0.007538, "rang": 8 },
        { "wort": "beschluss", "tfidf": 0.007134, "rang": 9 },
        { "wort": "deutschen", "tfidf": 0.006955, "rang": 10 },
        { "wort": "grundgesetzes", "tfidf": 0.006259, "rang": 11 },
        { "wort": "europäischen", "tfidf": 0.006259, "rang": 12 },
        { "wort": "wandel", "tfidf": 0.006147, "rang": 13 },
        { "wort": "privatangelegenheit", "tfidf": 0.006147, "rang": 14 },
        { "wort": "einvernehmens", "tfidf": 0.006147, "rang": 15 },
        { "wort": "vernetzte", "tfidf": 0.006147, "rang": 16 },
        { "wort": "ausschüssen", "tfidf": 0.006147, "rang": 17 },
        {
          "wort": "weltgesundheitsorganisation",
          "tfidf": 0.006147,
          "rang": 18
        },
        { "wort": "vertrages", "tfidf": 0.006147, "rang": 19 },
        { "wort": "arbeitsweise", "tfidf": 0.006147, "rang": 20 },
        { "wort": "aufbruch", "tfidf": 0.006147, "rang": 21 },
        { "wort": "geschäftsordnung", "tfidf": 0.005945, "rang": 22 },
        { "wort": "unterstützen", "tfidf": 0.005564, "rang": 23 },
        { "wort": "jahre", "tfidf": 0.004868, "rang": 24 },
        { "wort": "einheit", "tfidf": 0.003769, "rang": 25 },
        { "wort": "herstellung", "tfidf": 0.003769, "rang": 26 },
        { "wort": "enquete-kommission", "tfidf": 0.003769, "rang": 27 },
        { "wort": "lehren", "tfidf": 0.003769, "rang": 28 },
        { "wort": "afghanistan", "tfidf": 0.003769, "rang": 29 },
        { "wort": "künftige", "tfidf": 0.003769, "rang": 30 },
        { "wort": "mitglieder", "tfidf": 0.003769, "rang": 31 },
        { "wort": "gedenken", "tfidf": 0.003769, "rang": 32 },
        { "wort": "globalen", "tfidf": 0.003769, "rang": 33 },
        { "wort": "parlamentarischen", "tfidf": 0.003769, "rang": 34 },
        { "wort": "europa", "tfidf": 0.003567, "rang": 35 },
        { "wort": "europäische", "tfidf": 0.003567, "rang": 36 },
        { "wort": "engagement", "tfidf": 0.003567, "rang": 37 },
        { "wort": "änderung", "tfidf": 0.003477, "rang": 38 },
        { "wort": "bürgerrates", "tfidf": 0.003073, "rang": 39 },
        { "wort": "israelfeindlichkeit", "tfidf": 0.003073, "rang": 40 },
        { "wort": "diskursraum", "tfidf": 0.003073, "rang": 41 },
        { "wort": "geschädigten", "tfidf": 0.003073, "rang": 42 },
        { "wort": "organisierten", "tfidf": 0.003073, "rang": 43 },
        { "wort": "dopingsystems", "tfidf": 0.003073, "rang": 44 },
        { "wort": "opfergruppe", "tfidf": 0.003073, "rang": 45 },
        { "wort": "epochenwechsel", "tfidf": 0.003073, "rang": 46 },
        { "wort": "friedliche", "tfidf": 0.003073, "rang": 47 },
        { "wort": "talente", "tfidf": 0.003073, "rang": 48 },
        { "wort": "garantiert", "tfidf": 0.003073, "rang": 49 },
        { "wort": "georgiens", "tfidf": 0.003073, "rang": 50 }
      ],
      "SPD": [
        { "wort": "weitergeltung", "tfidf": 0.89588, "rang": 1 },
        { "wort": "geschäftsordnungsrecht", "tfidf": 0.89588, "rang": 2 }
      ]
    },
    "top_authors": {
      "AfD": [
        { "vorname": "Marc", "nachname": "Bernhard", "anzahl": 63 },
        { "vorname": "Martin", "nachname": "Sichert", "anzahl": 62 },
        { "vorname": "Stephan", "nachname": "Protschka", "anzahl": 47 },
        { "vorname": "René", "nachname": "Springer", "anzahl": 38 },
        { "vorname": "Leif-Erik", "nachname": "Holm", "anzahl": 36 },
        { "vorname": "Dr. Götz", "nachname": "Frömming", "anzahl": 35 },
        { "vorname": "Stephan", "nachname": "Brandner", "anzahl": 35 },
        { "vorname": "Dr. Christina", "nachname": "Baum", "anzahl": 33 },
        { "vorname": "Nicole", "nachname": "Höchst", "anzahl": 33 },
        { "vorname": "Kay", "nachname": "Gottschalk", "anzahl": 33 }
      ],
      "FDP": [
        { "vorname": "Dr. Lukas", "nachname": "Köhler", "anzahl": 4 },
        { "vorname": "Carina", "nachname": "Konrad", "anzahl": 4 },
        { "vorname": "Christoph", "nachname": "Meyer", "anzahl": 3 },
        { "vorname": "Renata", "nachname": "Alt", "anzahl": 3 },
        { "vorname": "Konstantin", "nachname": "Kuhle", "anzahl": 3 },
        { "vorname": "Frank", "nachname": "Schäffler", "anzahl": 1 },
        { "vorname": "Manfred", "nachname": "Todtenhausen", "anzahl": 1 },
        { "vorname": "Judith", "nachname": "Skudelny", "anzahl": 1 },
        { "vorname": "Anja", "nachname": "Schulz", "anzahl": 1 },
        { "vorname": "Ulrike", "nachname": "Harzer", "anzahl": 1 }
      ],
      "CDU/CSU": [
        { "vorname": "Friedrich", "nachname": "Merz", "anzahl": 2 },
        { "vorname": "Alexander", "nachname": "Dobrindt", "anzahl": 2 }
      ],
      "Die Linke": [
        { "vorname": "Susanne", "nachname": "Ferschl", "anzahl": 43 },
        { "vorname": "Dr. Gesine", "nachname": "Lötzsch", "anzahl": 39 },
        { "vorname": "Nicole", "nachname": "Gohlke", "anzahl": 28 },
        { "vorname": "Kathrin", "nachname": "Vogler", "anzahl": 17 },
        { "vorname": "Jan", "nachname": "Korte", "anzahl": 16 },
        { "vorname": "Clara", "nachname": "Bünger", "anzahl": 15 },
        { "vorname": "Gökay", "nachname": "Akbulut", "anzahl": 15 },
        { "vorname": "Caren", "nachname": "Lay", "anzahl": 13 },
        { "vorname": "Christian", "nachname": "Görke", "anzahl": 13 },
        { "vorname": "Ina", "nachname": "Latendorf", "anzahl": 12 }
      ]
    }
  },
  "Kleine Anfrage": {
    "counts_by_party": [
      { "party": "AfD", "count": 2013 },
      { "party": "CDU/CSU", "count": 1097 },
      { "party": "Die Linke", "count": 966 },
      { "party": "FDP", "count": 65 }
    ],
    "timeline": {
      "months": [
        "2021-11",
        "2021-12",
        "2022-01",
        "2022-02",
        "2022-03",
        "2022-04",
        "2022-05",
        "2022-06",
        "2022-07",
        "2022-08",
        "2022-09",
        "2022-10",
        "2022-11",
        "2022-12",
        "2023-01",
        "2023-02",
        "2023-03",
        "2023-04",
        "2023-05",
        "2023-06",
        "2023-07",
        "2023-08",
        "2023-09",
        "2023-10",
        "2023-11",
        "2023-12",
        "2024-01",
        "2024-02",
        "2024-03",
        "2024-04",
        "2024-05",
        "2024-06",
        "2024-07",
        "2024-08",
        "2024-09",
        "2024-10",
        "2024-11",
        "2024-12",
        "2025-01",
        "2025-02",
        "2025-03"
      ],
      "series": [
        {
          "party": "CDU/CSU",
          "counts": [
            0, 6, 7, 17, 22, 24, 24, 27, 17, 31, 28, 37, 31, 32, 27, 19, 44, 28,
            40, 43, 36, 33, 29, 24, 30, 41, 30, 30, 43, 34, 27, 27, 28, 37, 23,
            34, 14, 23, 40, 10, 0
          ]
        },
        {
          "party": "AfD",
          "counts": [
            52, 25, 45, 59, 67, 33, 68, 65, 71, 31, 101, 56, 59, 34, 68, 56, 49,
            43, 54, 54, 60, 40, 62, 44, 61, 44, 36, 52, 52, 42, 37, 39, 36, 78,
            72, 43, 32, 36, 39, 13, 5
          ]
        },
        {
          "party": "Die Linke",
          "counts": [
            21, 28, 17, 44, 43, 37, 45, 61, 49, 51, 48, 28, 29, 36, 45, 28, 31,
            44, 30, 41, 35, 47, 32, 27, 61, 8, 0, 0, 0, 0, 0, 0, 0, 0, 0, 0, 0,
            0, 0, 0, 0
          ]
        },
        {
          "party": "FDP",
          "counts": [
            0, 0, 0, 0, 0, 0, 0, 0, 0, 0, 0, 0, 0, 0, 0, 0, 0, 0, 0, 0, 0, 0, 0,
            0, 0, 0, 0, 0, 0, 0, 0, 0, 0, 0, 0, 0, 0, 45, 12, 8, 0
          ]
        }
      ]
    },
    "word_freq": {
      "AfD": [
        { "wort": "talbrücke", "tfidf": 0.005801, "rang": 1 },
        { "wort": "kriminalitätsentwicklung", "tfidf": 0.005423, "rang": 2 },
        { "wort": "gesamtjahr", "tfidf": 0.003784, "rang": 3 },
        { "wort": "effektivität", "tfidf": 0.003153, "rang": 4 },
        { "wort": "wirtschaftlichen", "tfidf": 0.003153, "rang": 5 },
        { "wort": "halbjahr", "tfidf": 0.00309, "rang": 6 },
        { "wort": "autobahnbaustellen", "tfidf": 0.003027, "rang": 7 },
        { "wort": "bundestagsdrucksache", "tfidf": 0.002774, "rang": 8 },
        { "wort": "kleine", "tfidf": 0.002748, "rang": 9 },
        { "wort": "kriminalitätsfelder", "tfidf": 0.002522, "rang": 10 },
        { "wort": "hauptbahnhof", "tfidf": 0.002459, "rang": 11 },
        { "wort": "republik", "tfidf": 0.002396, "rang": 12 },
        { "wort": "zustand", "tfidf": 0.002198, "rang": 13 },
        { "wort": "aktueller", "tfidf": 0.002172, "rang": 14 },
        { "wort": "autobahn", "tfidf": 0.002146, "rang": 15 },
        { "wort": "korrekturbitten", "tfidf": 0.002144, "rang": 16 },
        { "wort": "mögliche", "tfidf": 0.002041, "rang": 17 },
        { "wort": "jahr", "tfidf": 0.001911, "rang": 18 },
        { "wort": "januar", "tfidf": 0.001829, "rang": 19 },
        { "wort": "entwicklungszusammenarbeit", "tfidf": 0.001701, "rang": 20 },
        { "wort": "bezug", "tfidf": 0.00164, "rang": 21 },
        { "wort": "ende", "tfidf": 0.00164, "rang": 22 },
        { "wort": "förderung", "tfidf": 0.001623, "rang": 23 },
        { "wort": "zeitraum", "tfidf": 0.001513, "rang": 24 },
        { "wort": "versorgungslage", "tfidf": 0.001513, "rang": 25 },
        { "wort": "aufhaltende", "tfidf": 0.001387, "rang": 26 },
        { "wort": "stichtag", "tfidf": 0.001387, "rang": 27 },
        { "wort": "versorgungsgrad", "tfidf": 0.001387, "rang": 28 },
        { "wort": "ukraine", "tfidf": 0.001361, "rang": 29 },
        { "wort": "entwicklung", "tfidf": 0.001282, "rang": 30 },
        { "wort": "zulassung", "tfidf": 0.001261, "rang": 31 },
        { "wort": "partner", "tfidf": 0.001261, "rang": 32 },
        { "wort": "erfassung", "tfidf": 0.001261, "rang": 33 },
        { "wort": "illegal", "tfidf": 0.001261, "rang": 34 },
        { "wort": "grenzkontrollen", "tfidf": 0.001261, "rang": 35 },
        { "wort": "außengrenze", "tfidf": 0.001261, "rang": 36 },
        { "wort": "bundespolizei", "tfidf": 0.001178, "rang": 37 },
        { "wort": "juni", "tfidf": 0.001178, "rang": 38 },
        { "wort": "zweiten", "tfidf": 0.001152, "rang": 39 },
        { "wort": "politische", "tfidf": 0.001135, "rang": 40 },
        { "wort": "parteibüros", "tfidf": 0.001135, "rang": 41 },
        { "wort": "comirnaty", "tfidf": 0.001135, "rang": 42 },
        { "wort": "umfragewerte", "tfidf": 0.001135, "rang": 43 },
        { "wort": "einzelplan", "tfidf": 0.001135, "rang": 44 },
        { "wort": "einzelheiten", "tfidf": 0.001135, "rang": 45 },
        { "wort": "äußerungen", "tfidf": 0.001072, "rang": 46 },
        { "wort": "einreisen", "tfidf": 0.001072, "rang": 47 },
        { "wort": "politisch", "tfidf": 0.001072, "rang": 48 },
        { "wort": "wahlplakate", "tfidf": 0.001009, "rang": 49 },
        { "wort": "gewaltdelikten", "tfidf": 0.001009, "rang": 50 }
      ],
      "CDU/CSU": [
        { "wort": "gebäudeenergiegesetzes", "tfidf": 0.003365, "rang": 1 },
        { "wort": "avisierten", "tfidf": 0.003107, "rang": 2 },
        { "wort": "aktueller", "tfidf": 0.002632, "rang": 3 },
        { "wort": "bilanz", "tfidf": 0.002459, "rang": 4 },
        { "wort": "bundesverkehrswegeplans", "tfidf": 0.00233, "rang": 5 },
        { "wort": "bundesministers", "tfidf": 0.0022, "rang": 6 },
        { "wort": "digitales", "tfidf": 0.0022, "rang": 7 },
        { "wort": "neubau", "tfidf": 0.0022, "rang": 8 },
        { "wort": "verkehr", "tfidf": 0.002071, "rang": 9 },
        { "wort": "özdemir", "tfidf": 0.002071, "rang": 10 },
        { "wort": "versorgung", "tfidf": 0.002071, "rang": 11 },
        { "wort": "forschungs", "tfidf": 0.002071, "rang": 12 },
        { "wort": "studentinnen", "tfidf": 0.002071, "rang": 13 },
        { "wort": "fachschülerinnen", "tfidf": 0.002071, "rang": 14 },
        { "wort": "fachschüler", "tfidf": 0.002071, "rang": 15 },
        { "wort": "forschung", "tfidf": 0.00188, "rang": 16 },
        { "wort": "pläne", "tfidf": 0.001812, "rang": 17 },
        { "wort": "cem", "tfidf": 0.001812, "rang": 18 },
        { "wort": "euro-zuschusses", "tfidf": 0.001812, "rang": 19 },
        { "wort": "bundesministeriums", "tfidf": 0.001719, "rang": 20 },
        { "wort": "reaktivierung", "tfidf": 0.001683, "rang": 21 },
        { "wort": "landwirtschaft", "tfidf": 0.001558, "rang": 22 },
        { "wort": "amtszeit", "tfidf": 0.001553, "rang": 23 },
        { "wort": "breitbandförderung", "tfidf": 0.001553, "rang": 24 },
        { "wort": "energie", "tfidf": 0.001553, "rang": 25 },
        { "wort": "bundes", "tfidf": 0.00145, "rang": 26 },
        { "wort": "bildung", "tfidf": 0.001397, "rang": 27 },
        { "wort": "einjahresbilanz", "tfidf": 0.001294, "rang": 28 },
        { "wort": "gigabitstrategie", "tfidf": 0.001294, "rang": 29 },
        { "wort": "halbzeitbilanz", "tfidf": 0.001294, "rang": 30 },
        { "wort": "förderung", "tfidf": 0.001289, "rang": 31 },
        { "wort": "bundesministerium", "tfidf": 0.001236, "rang": 32 },
        { "wort": "digitalisierung", "tfidf": 0.001165, "rang": 33 },
        { "wort": "verteidigung", "tfidf": 0.001165, "rang": 34 },
        { "wort": "auszahlung", "tfidf": 0.001165, "rang": 35 },
        { "wort": "ergebnisse", "tfidf": 0.001165, "rang": 36 },
        { "wort": "bildungs", "tfidf": 0.001036, "rang": 37 },
        { "wort": "soziales", "tfidf": 0.001036, "rang": 38 },
        { "wort": "ambulanten", "tfidf": 0.001036, "rang": 39 },
        { "wort": "regelungen", "tfidf": 0.001036, "rang": 40 },
        { "wort": "cities", "tfidf": 0.001036, "rang": 41 },
        { "wort": "sachverhaltsaufklärung", "tfidf": 0.001036, "rang": 42 },
        { "wort": "stark-watzinger", "tfidf": 0.001036, "rang": 43 },
        { "wort": "verordnung", "tfidf": 0.001036, "rang": 44 },
        { "wort": "iris", "tfidf": 0.001036, "rang": 45 },
        { "wort": "mobilfunknetz", "tfidf": 0.001036, "rang": 46 },
        { "wort": "ernährungswirtschaft", "tfidf": 0.001036, "rang": 47 },
        { "wort": "innovationsförderung", "tfidf": 0.001036, "rang": 48 },
        { "wort": "satelliteninternet", "tfidf": 0.001036, "rang": 49 },
        { "wort": "eu-programms", "tfidf": 0.001036, "rang": 50 }
      ],
      "Die Linke": [
        { "wort": "mindestlohnbetrug", "tfidf": 0.009948, "rang": 1 },
        { "wort": "mindestlohns", "tfidf": 0.009948, "rang": 2 },
        { "wort": "quartal", "tfidf": 0.00907, "rang": 3 },
        { "wort": "kriminalität-rechts", "tfidf": 0.006144, "rang": 4 },
        { "wort": "rechtsextreme", "tfidf": 0.005852, "rang": 5 },
        { "wort": "kontrollen", "tfidf": 0.00512, "rang": 6 },
        { "wort": "politisch", "tfidf": 0.00395, "rang": 7 },
        { "wort": "motivierte", "tfidf": 0.003804, "rang": 8 },
        { "wort": "arbeitsbedingungen", "tfidf": 0.003511, "rang": 9 },
        { "wort": "erkenntnisse", "tfidf": 0.003511, "rang": 10 },
        { "wort": "neonazis", "tfidf": 0.003511, "rang": 11 },
        { "wort": "extremen", "tfidf": 0.003511, "rang": 12 },
        { "wort": "proteste", "tfidf": 0.003218, "rang": 13 },
        { "wort": "dritten", "tfidf": 0.002926, "rang": 14 },
        { "wort": "aufmärsche", "tfidf": 0.002926, "rang": 15 },
        { "wort": "rechtsextremen", "tfidf": 0.002633, "rang": 16 },
        { "wort": "flüchtlingsunterkünfte", "tfidf": 0.002633, "rang": 17 },
        { "wort": "islamfeindlichkeit", "tfidf": 0.002633, "rang": 18 },
        { "wort": "antimuslimische", "tfidf": 0.002633, "rang": 19 },
        { "wort": "musikveranstaltungen", "tfidf": 0.002633, "rang": 20 },
        { "wort": "munitions", "tfidf": 0.002633, "rang": 21 },
        { "wort": "sicherheitsbehörden", "tfidf": 0.002341, "rang": 22 },
        { "wort": "rechten", "tfidf": 0.002341, "rang": 23 },
        { "wort": "sportstätten", "tfidf": 0.002341, "rang": 24 },
        { "wort": "entwicklung", "tfidf": 0.002247, "rang": 25 },
        { "wort": "asylstatistik", "tfidf": 0.002194, "rang": 26 },
        { "wort": "ermittlungen", "tfidf": 0.002194, "rang": 27 },
        { "wort": "einhaltung", "tfidf": 0.002064, "rang": 28 },
        { "wort": "verbindungen", "tfidf": 0.002048, "rang": 29 },
        { "wort": "gruppierung", "tfidf": 0.002048, "rang": 30 },
        { "wort": "finanzermittlungen", "tfidf": 0.002048, "rang": 31 },
        { "wort": "neonazistischen", "tfidf": 0.002048, "rang": 32 },
        { "wort": "trotz", "tfidf": 0.002048, "rang": 33 },
        { "wort": "vorhabenplanung", "tfidf": 0.002048, "rang": 34 },
        { "wort": "jahr", "tfidf": 0.001761, "rang": 35 },
        { "wort": "ausreisen", "tfidf": 0.001756, "rang": 36 },
        { "wort": "rechtsextremisten", "tfidf": 0.001756, "rang": 37 },
        { "wort": "gesuchter", "tfidf": 0.001756, "rang": 38 },
        { "wort": "reichsbürger", "tfidf": 0.001756, "rang": 39 },
        { "wort": "polizei", "tfidf": 0.001756, "rang": 40 },
        { "wort": "vernetzung", "tfidf": 0.001756, "rang": 41 },
        { "wort": "rüstungsexporte", "tfidf": 0.001609, "rang": 42 },
        { "wort": "lebender", "tfidf": 0.001463, "rang": 43 },
        { "wort": "übergriffe", "tfidf": 0.001463, "rang": 44 },
        { "wort": "arbeitsuchende", "tfidf": 0.001463, "rang": 45 },
        { "wort": "halbjahr", "tfidf": 0.001463, "rang": 46 },
        { "wort": "schutzsuchenden", "tfidf": 0.001463, "rang": 47 },
        { "wort": "bundesanwaltschaft", "tfidf": 0.001463, "rang": 48 },
        { "wort": "förderung", "tfidf": 0.001457, "rang": 49 },
        { "wort": "bund", "tfidf": 0.001457, "rang": 50 }
      ],
      "FDP": [
        { "wort": "notsituation", "tfidf": 0.012836, "rang": 1 },
        { "wort": "lücken", "tfidf": 0.012836, "rang": 2 },
        { "wort": "klimaschutzwirkung", "tfidf": 0.012836, "rang": 3 },
        { "wort": "bundesaußenministerin", "tfidf": 0.006418, "rang": 4 },
        { "wort": "russischem", "tfidf": 0.006418, "rang": 5 },
        { "wort": "feministischer", "tfidf": 0.006418, "rang": 6 },
        { "wort": "außergewöhnliche", "tfidf": 0.006418, "rang": 7 },
        { "wort": "ukrainehilfen", "tfidf": 0.006418, "rang": 8 },
        { "wort": "bundeshaushalt", "tfidf": 0.006418, "rang": 9 },
        { "wort": "ukraine-hilfe", "tfidf": 0.006418, "rang": 10 },
        { "wort": "generationengerechtigkeit", "tfidf": 0.006418, "rang": 11 },
        { "wort": "energiepolitik", "tfidf": 0.006418, "rang": 12 },
        { "wort": "hilfswerk", "tfidf": 0.006418, "rang": 13 },
        { "wort": "palästina-flüchtlinge", "tfidf": 0.006418, "rang": 14 },
        { "wort": "nahen", "tfidf": 0.006418, "rang": 15 },
        { "wort": "kohleausstiegs", "tfidf": 0.006418, "rang": 16 },
        { "wort": "steueraufkommen", "tfidf": 0.006418, "rang": 17 },
        { "wort": "einkommen", "tfidf": 0.006418, "rang": 18 },
        { "wort": "vermögenssteuer", "tfidf": 0.006418, "rang": 19 },
        { "wort": "tierhaltungskennzeichen", "tfidf": 0.006418, "rang": 20 },
        { "wort": "wettbewerbsverzerrungen", "tfidf": 0.006418, "rang": 21 },
        { "wort": "onlinehändler", "tfidf": 0.006418, "rang": 22 },
        { "wort": "planwagenfahrten", "tfidf": 0.006418, "rang": 23 },
        { "wort": "brauchtumspflege", "tfidf": 0.006418, "rang": 24 },
        { "wort": "verzeichnis", "tfidf": 0.006418, "rang": 25 },
        { "wort": "pflegeanwendungen", "tfidf": 0.006418, "rang": 26 },
        { "wort": "neugestaltung", "tfidf": 0.006418, "rang": 27 },
        { "wort": "bahnhofsvorplatzes", "tfidf": 0.006418, "rang": 28 },
        { "wort": "games-förderung", "tfidf": 0.006418, "rang": 29 },
        { "wort": "modells", "tfidf": 0.006418, "rang": 30 },
        { "wort": "volunteers", "tfidf": 0.006418, "rang": 31 },
        { "wort": "sportgroßveranstaltungen", "tfidf": 0.006418, "rang": 32 },
        { "wort": "brigade", "tfidf": 0.006418, "rang": 33 },
        { "wort": "litauen", "tfidf": 0.006418, "rang": 34 },
        { "wort": "pflegender", "tfidf": 0.006418, "rang": 35 },
        { "wort": "jugendlicher", "tfidf": 0.006418, "rang": 36 },
        { "wort": "wasserwiederverwendung", "tfidf": 0.006418, "rang": 37 },
        { "wort": "anwendungsbereiche", "tfidf": 0.006418, "rang": 38 },
        { "wort": "eu-regulierung", "tfidf": 0.006418, "rang": 39 },
        { "wort": "züchtungstechniken", "tfidf": 0.006418, "rang": 40 },
        { "wort": "hochvermögende", "tfidf": 0.006418, "rang": 41 },
        { "wort": "cyberangriffen", "tfidf": 0.006418, "rang": 42 },
        { "wort": "bankensektors", "tfidf": 0.006418, "rang": 43 },
        { "wort": "verbriefungen", "tfidf": 0.006418, "rang": 44 },
        { "wort": "tariftreuegesetz", "tfidf": 0.006418, "rang": 45 },
        { "wort": "förderentscheidung", "tfidf": 0.006418, "rang": 46 },
        { "wort": "krisenchat", "tfidf": 0.006418, "rang": 47 },
        { "wort": "energieerzeugung", "tfidf": 0.006418, "rang": 48 },
        { "wort": "biogas", "tfidf": 0.006418, "rang": 49 },
        { "wort": "entwicklungsplan", "tfidf": 0.006418, "rang": 50 }
      ]
    },
    "top_authors": {
      "AfD": [
        { "vorname": "Stephan", "nachname": "Brandner", "anzahl": 269 },
        { "vorname": "Martin", "nachname": "Hess", "anzahl": 258 },
        { "vorname": "Dr. Bernd", "nachname": "Baumann", "anzahl": 202 },
        { "vorname": "Tobias Matthias", "nachname": "Peterka", "anzahl": 140 },
        { "vorname": "Markus", "nachname": "Frohnmaier", "anzahl": 134 },
        { "vorname": "Stephan", "nachname": "Protschka", "anzahl": 133 },
        { "vorname": "René", "nachname": "Springer", "anzahl": 128 },
        { "vorname": "Dietmar", "nachname": "Friedhoff", "anzahl": 107 },
        { "vorname": "Thomas", "nachname": "Seitz", "anzahl": 104 },
        { "vorname": "Leif-Erik", "nachname": "Holm", "anzahl": 99 }
      ],
      "FDP": [
        { "vorname": "Christoph", "nachname": "Meyer", "anzahl": 25 },
        { "vorname": "Dr. Lukas", "nachname": "Köhler", "anzahl": 12 },
        { "vorname": "Konstantin", "nachname": "Kuhle", "anzahl": 10 },
        { "vorname": "Otto", "nachname": "Fricke", "anzahl": 9 },
        { "vorname": "Renata", "nachname": "Alt", "anzahl": 8 },
        { "vorname": "Carina", "nachname": "Konrad", "anzahl": 7 },
        {
          "vorname": "Michael Georg Link",
          "nachname": "(Heilbronn)",
          "anzahl": 5
        },
        { "vorname": "Anja", "nachname": "Schulz", "anzahl": 5 },
        { "vorname": "Gyde", "nachname": "Jensen", "anzahl": 4 },
        { "vorname": "Till", "nachname": "Mansmann", "anzahl": 3 }
      ],
      "Die Linke": [
        { "vorname": "Nicole", "nachname": "Gohlke", "anzahl": 414 },
        { "vorname": "Martina", "nachname": "Renner", "anzahl": 177 },
        { "vorname": "Susanne", "nachname": "Ferschl", "anzahl": 147 },
        { "vorname": "Dr. Gesine", "nachname": "Lötzsch", "anzahl": 118 },
        { "vorname": "Clara", "nachname": "Bünger", "anzahl": 107 },
        { "vorname": "Sevim", "nachname": "Dagdelen", "anzahl": 97 },
        { "vorname": "Gökay", "nachname": "Akbulut", "anzahl": 82 },
        { "vorname": "Andrej", "nachname": "Hunko", "anzahl": 78 },
        { "vorname": "Petra", "nachname": "Pau", "anzahl": 65 },
        { "vorname": "Ali", "nachname": "Al-Dailami", "anzahl": 60 }
      ]
    }
  },
  "Große Anfrage": {
    "counts_by_party": [
      { "party": "AfD", "count": 20 },
      { "party": "CDU/CSU", "count": 14 },
      { "party": "Die Linke", "count": 1 }
    ],
    "timeline": {
      "months": [
        "2022-02",
        "2022-04",
        "2022-07",
        "2022-08",
        "2022-09",
        "2023-02",
        "2023-03",
        "2023-05",
        "2023-06",
        "2023-09",
        "2023-10",
        "2023-12",
        "2024-01",
        "2024-03",
        "2024-04",
        "2024-05",
        "2024-07",
        "2024-12"
      ],
      "series": [
        {
          "party": "CDU/CSU",
          "counts": [1, 1, 0, 1, 1, 0, 1, 0, 0, 0, 3, 0, 0, 2, 1, 0, 2, 1]
        },
        {
          "party": "AfD",
          "counts": [0, 0, 2, 0, 1, 1, 0, 3, 1, 1, 0, 1, 2, 0, 2, 3, 1, 2]
        },
        {
          "party": "Die Linke",
          "counts": [0, 0, 0, 0, 0, 0, 0, 0, 0, 0, 1, 0, 0, 0, 0, 0, 0, 0]
        }
      ]
    },
    "word_freq": {
      "AfD": [
        { "wort": "deutschland", "tfidf": 0.018159, "rang": 1 },
        { "wort": "detailfragen", "tfidf": 0.009079, "rang": 2 },
        { "wort": "schuldenerlassen", "tfidf": 0.009079, "rang": 3 },
        { "wort": "bundesrepublik", "tfidf": 0.009079, "rang": 4 },
        { "wort": "gegenüber", "tfidf": 0.009079, "rang": 5 },
        { "wort": "anderen", "tfidf": 0.009079, "rang": 6 },
        { "wort": "staaten", "tfidf": 0.009079, "rang": 7 },
        { "wort": "zeitraum", "tfidf": 0.009079, "rang": 8 },
        { "wort": "vom", "tfidf": 0.009079, "rang": 9 },
        { "wort": "januar", "tfidf": 0.009079, "rang": 10 },
        { "wort": "dezember", "tfidf": 0.009079, "rang": 11 },
        { "wort": "politikergedenkstiftungen", "tfidf": 0.009079, "rang": 12 },
        { "wort": "verdienste", "tfidf": 0.009079, "rang": 13 },
        { "wort": "beauftragten", "tfidf": 0.009079, "rang": 14 },
        { "wort": "koordinatoren", "tfidf": 0.009079, "rang": 15 },
        { "wort": "kenntnisse", "tfidf": 0.009079, "rang": 16 },
        { "wort": "nachgeordneter", "tfidf": 0.009079, "rang": 17 },
        { "wort": "behörden", "tfidf": 0.009079, "rang": 18 },
        { "wort": "vorgebliche", "tfidf": 0.009079, "rang": 19 },
        { "wort": "geheimtreffen", "tfidf": 0.009079, "rang": 20 },
        { "wort": "potsdam", "tfidf": 0.009079, "rang": 21 },
        { "wort": "zusammenarbeit", "tfidf": 0.009079, "rang": 22 },
        { "wort": "unternehmensverbund", "tfidf": 0.009079, "rang": 23 },
        { "wort": "correctiv", "tfidf": 0.009079, "rang": 24 },
        { "wort": "sozialstaat", "tfidf": 0.009079, "rang": 25 },
        { "wort": "zuwanderung", "tfidf": 0.009079, "rang": 26 },
        { "wort": "ausgaben", "tfidf": 0.009079, "rang": 27 },
        { "wort": "eigene", "tfidf": 0.009079, "rang": 28 },
        { "wort": "aufgabenwahrnehmung", "tfidf": 0.009079, "rang": 29 },
        { "wort": "außendarstellung", "tfidf": 0.009079, "rang": 30 },
        { "wort": "migrationspolitische", "tfidf": 0.009079, "rang": 31 },
        { "wort": "effekte", "tfidf": 0.009079, "rang": 32 },
        { "wort": "deutschen", "tfidf": 0.009079, "rang": 33 },
        { "wort": "entwicklungszusammenarbeit", "tfidf": 0.009079, "rang": 34 },
        { "wort": "rücküberweisungen", "tfidf": 0.009079, "rang": 35 },
        { "wort": "hintergrund", "tfidf": 0.009079, "rang": 36 },
        { "wort": "studie", "tfidf": 0.009079, "rang": 37 },
        { "wort": "entwicklungsprogramms", "tfidf": 0.009079, "rang": 38 },
        { "wort": "vereinten", "tfidf": 0.009079, "rang": 39 },
        { "wort": "nationen", "tfidf": 0.009079, "rang": 40 },
        { "wort": "the", "tfidf": 0.009079, "rang": 41 },
        { "wort": "scaling", "tfidf": 0.009079, "rang": 42 },
        { "wort": "fences", "tfidf": 0.009079, "rang": 43 },
        { "wort": "voices", "tfidf": 0.009079, "rang": 44 },
        { "wort": "irregular", "tfidf": 0.009079, "rang": 45 },
        { "wort": "african", "tfidf": 0.009079, "rang": 46 },
        { "wort": "migrants", "tfidf": 0.009079, "rang": 47 },
        { "wort": "europe", "tfidf": 0.009079, "rang": 48 },
        { "wort": "sprengung", "tfidf": 0.009079, "rang": 49 },
        { "wort": "nord", "tfidf": 0.009079, "rang": 50 }
      ],
      "CDU/CSU": [
        { "wort": "pläne", "tfidf": 0.030517, "rang": 1 },
        { "wort": "umsetzung", "tfidf": 0.030517, "rang": 2 },
        { "wort": "hinsichtlich", "tfidf": 0.030517, "rang": 3 },
        {
          "wort": "wissenschaftszeitvertragsgesetzes",
          "tfidf": 0.030517,
          "rang": 4
        },
        { "wort": "rückforderung", "tfidf": 0.015259, "rang": 5 },
        { "wort": "unrecht", "tfidf": 0.015259, "rang": 6 },
        { "wort": "erstatteten", "tfidf": 0.015259, "rang": 7 },
        { "wort": "steuern", "tfidf": 0.015259, "rang": 8 },
        { "wort": "cumex-geschäften", "tfidf": 0.015259, "rang": 9 },
        { "wort": "bank", "tfidf": 0.015259, "rang": 10 },
        { "wort": "olaf", "tfidf": 0.015259, "rang": 11 },
        { "wort": "scholz", "tfidf": 0.015259, "rang": 12 },
        { "wort": "befassung", "tfidf": 0.015259, "rang": 13 },
        { "wort": "vorgang", "tfidf": 0.015259, "rang": 14 },
        { "wort": "heimatpolitik", "tfidf": 0.015259, "rang": 15 },
        { "wort": "herstellung", "tfidf": 0.015259, "rang": 16 },
        { "wort": "gleichwertiger", "tfidf": 0.015259, "rang": 17 },
        { "wort": "lebensverhältnisse", "tfidf": 0.015259, "rang": 18 },
        { "wort": "sachverhaltsaufklärung", "tfidf": 0.015259, "rang": 19 },
        { "wort": "bettina", "tfidf": 0.015259, "rang": 20 },
        { "wort": "stark-watzinger", "tfidf": 0.015259, "rang": 21 },
        { "wort": "fördermittel-affäre", "tfidf": 0.015259, "rang": 22 },
        { "wort": "stabilität", "tfidf": 0.015259, "rang": 23 },
        { "wort": "finanzierung", "tfidf": 0.015259, "rang": 24 },
        { "wort": "sozialversicherung", "tfidf": 0.015259, "rang": 25 },
        { "wort": "bearbeitungsdauer", "tfidf": 0.015259, "rang": 26 },
        { "wort": "anträgen", "tfidf": 0.015259, "rang": 27 },
        { "wort": "auslands-bafög", "tfidf": 0.015259, "rang": 28 },
        { "wort": "rechts", "tfidf": 0.015259, "rang": 29 },
        { "wort": "schnelles", "tfidf": 0.015259, "rang": 30 },
        { "wort": "internet", "tfidf": 0.015259, "rang": 31 },
        {
          "wort": "tk-mindestversorgungsverordnung",
          "tfidf": 0.015259,
          "rang": 32
        },
        { "wort": "tkmv", "tfidf": 0.015259, "rang": 33 },
        { "wort": "projektförderung", "tfidf": 0.015259, "rang": 34 },
        { "wort": "grundlagenforschung", "tfidf": 0.015259, "rang": 35 },
        { "wort": "long", "tfidf": 0.015259, "rang": 36 },
        { "wort": "cfs", "tfidf": 0.015259, "rang": 37 },
        { "wort": "post-vac-syndrom", "tfidf": 0.015259, "rang": 38 },
        { "wort": "regierungspläne", "tfidf": 0.015259, "rang": 39 },
        { "wort": "digitalpaktes", "tfidf": 0.015259, "rang": 40 },
        { "wort": "weiteres", "tfidf": 0.015259, "rang": 41 },
        { "wort": "vorgehen", "tfidf": 0.015259, "rang": 42 },
        { "wort": "wettbewerbsfähigkeit", "tfidf": 0.015259, "rang": 43 },
        { "wort": "deutschlands", "tfidf": 0.015259, "rang": 44 },
        { "wort": "internationalen", "tfidf": 0.015259, "rang": 45 },
        { "wort": "steuerwettbewerb", "tfidf": 0.015259, "rang": 46 },
        { "wort": "beitrag", "tfidf": 0.015259, "rang": 47 },
        { "wort": "aufholen", "tfidf": 0.015259, "rang": 48 },
        { "wort": "pandemiebedingten", "tfidf": 0.015259, "rang": 49 },
        { "wort": "lernrückständen", "tfidf": 0.015259, "rang": 50 }
      ],
      "Die Linke": [
        { "wort": "verfügbarkeit", "tfidf": 0.366204, "rang": 1 },
        { "wort": "sauberem", "tfidf": 0.366204, "rang": 2 },
        { "wort": "wasser", "tfidf": 0.366204, "rang": 3 }
      ]
    },
    "top_authors": {
      "AfD": [
        { "vorname": "Stephan", "nachname": "Brandner", "anzahl": 4 },
        { "vorname": "Dr. Marc", "nachname": "Jongen", "anzahl": 4 },
        { "vorname": "Nicole", "nachname": "Höchst", "anzahl": 4 },
        { "vorname": "Kay", "nachname": "Gottschalk", "anzahl": 2 },
        { "vorname": "Dr. Götz", "nachname": "Frömming", "anzahl": 2 },
        { "vorname": "Martin Erwin", "nachname": "Renner", "anzahl": 2 },
        { "vorname": "René", "nachname": "Springer", "anzahl": 2 },
        { "vorname": "Stefan", "nachname": "Keuter", "anzahl": 2 },
        { "vorname": "Martin", "nachname": "Reichardt", "anzahl": 2 },
        { "vorname": "Jochen", "nachname": "Haug", "anzahl": 1 }
      ],
      "Die Linke": [
        { "vorname": "Ralph", "nachname": "Lenkert", "anzahl": 1 },
        { "vorname": "Ina", "nachname": "Latendorf", "anzahl": 1 }
      ]
    }
  }
}
